[
  {
    "lnglat": [114.24871,30.564246],
    "name": "月湖桥监测点",
    "user": "陈鸿琳",
    "mobile": "1376648987",
    "create": "2016-09-04",
    "temp": 59,
    "scrBefore": 70,
    "scrAfter": 63,
    "scrN0Before": 70,
    "scrN0After": 63,
    "scrN0AfterTime": "2019-01-05"
  }, {
    "lnglat": [114.267185,30.569456],
    "name": "武胜路监测点",
    "user": "蒋思渊",
    "mobile": "1376648987",
    "create": "2016-09-04",
    "temp": 59,
    "scrBefore": 70,
    "scrAfter": 63,
    "scrN0Before": 70,
    "scrN0After": 63,
    "scrN0AfterTime": "2019-01-05"
  }, {
    "lnglat": [114.276111,30.598255],
    "name": "取水楼监测点",
    "user": "姜浩天",
    "mobile": "1376648987",
    "create": "2016-09-04",
    "temp": 59,
    "scrBefore": 70,
    "scrAfter": 63,
    "scrN0Before": 70,
    "scrN0After": 63,
    "scrN0AfterTime": "2019-01-05"
  }, {
    "lnglat": [114.266069,30.547976],
    "name": "钟家村监测点",
    "user": "葛君豪",
    "mobile": "1376648987",
    "create": "2016-09-04",
    "temp": 59,
    "scrBefore": 70,
    "scrAfter": 63,
    "scrN0Before": 70,
    "scrN0After": 63,
    "scrN0AfterTime": "2019-01-05"
  }, {
    "lnglat": [114.310079,30.533339],
    "name": "首义路监测点",
    "user": "曹存志",
    "mobile": "1376648987",
    "create": "2016-09-04",
    "temp": 59,
    "scrBefore": 70,
    "scrAfter": 63,
    "scrN0Before": 70,
    "scrN0After": 63,
    "scrN0AfterTime": "2019-01-05"
  }, {
    "lnglat": [114.345666,30.588327],
    "name": "徐东监测点",
    "user": "祁骏臣",
    "mobile": "1376648987",
    "create": "2016-09-04",
    "temp": 59,
    "scrBefore": 70,
    "scrAfter": 63,
    "scrN0Before": 70,
    "scrN0After": 63,
    "scrN0AfterTime": "2019-01-05"
  }, {
    "lnglat": [114.379097,30.60072],
    "name": "园林路监测点",
    "user": "易序波",
    "mobile": "1376648987",
    "create": "2016-09-04",
    "temp": 59,
    "scrBefore": 70,
    "scrAfter": 63,
    "scrN0Before": 70,
    "scrN0After": 63,
    "scrN0AfterTime": "2019-01-05"
  }, {
    "lnglat": [114.369986,30.481305],
    "name": "南湖大道监测点",
    "user": "闫艺抒",
    "mobile": "1376648987",
    "create": "2016-09-04",
    "temp": 59,
    "scrBefore": 70,
    "scrAfter": 63,
    "scrN0Before": 70,
    "scrN0After": 63,
    "scrN0AfterTime": "2019-01-05"
  }
]